module/__init__.py
module/log.py
module/misc.py
zz_spider/KafakProduct.py
zz_spider/KafkaClient.py
zz_spider/KafkaConsume.py
zz_spider/KafkaInstant.py
zz_spider/RabbitMq.py
zz_spider/__init__.py
zz_spider-1.0.0.dist-info/LICENSE
zz_spider-1.0.0.dist-info/METADATA
zz_spider-1.0.0.dist-info/WHEEL
zz_spider-1.0.0.dist-info/top_level.txt
zz_spider-1.0.0.dist-info/RECORD
