Metadata-Version: 2.1
Name: zz-spider
Version: 1.0.0
Summary: python使用MQ的场景
Home-page: https://github.com/qpzzk/zz_spider
Author: zzk
Author-email: zzk_python@163.com
License: UNKNOWN
Platform: UNKNOWN
Classifier: Programming Language :: Python :: 3.7
Classifier: License :: OSI Approved :: MIT License
Classifier: Operating System :: OS Independent
License-File: LICENSE
Requires-Dist: requests (>=2.22.0)
Requires-Dist: pika (>=1.2.0)
Requires-Dist: retrying (>=1.3.3)
Requires-Dist: environs (==9.4.0)
Requires-Dist: confluent-kafka (==1.8.2)
Requires-Dist: kafka (==1.3.5)
Requires-Dist: kafka-python (==2.0.2)
Requires-Dist: pykafka (==2.8.0)
Requires-Dist: loguru (==0.5.3)
